[
  {
    "title": "Responsive News Site",
    "imageSrc": "projects/news-site.png",
    "description": "A responsive news website built to learn modern web development techniques.",
    "skills": ["HTML", "CSS", "JS"],
    "demo": "https://www.example.com",
    "source": "https://www.github.com"
  },
  {
    "title": "Keeper App",
    "imageSrc": "projects/keeper-app.png",
    "description": "A notes and to-do keeper app inspired by Google Keep.",
    "skills": ["React", "Express", "Node"],
    "demo": "https://www.example.com",
    "source": "https://www.github.com"
  },
  {
    "title": "Expense Tracker",
    "imageSrc": "projects/expense-tracker.png",
    "description": "A finance tracking app that allows users to manage and track their expenses.",
    "skills": ["React", "Express", "Node"],
    "demo": "https://www.example.com",
    "source": "https://www.github.com"
  }
]